wwl/LICENSE
wwl/__init__.py
wwl/propagation_scheme.py
wwl/utilities.py
wwl/wwl.py
wwl-0.1.2.dist-info/LICENSE
wwl-0.1.2.dist-info/WHEEL
wwl-0.1.2.dist-info/METADATA
wwl-0.1.2.dist-info/RECORD
